mcp_data_analyzer_main/__init__.py
mcp_data_analyzer_main/__main__.py
mcp_data_analyzer_main/cli.py
mcp_data_analyzer_main/core.py
mcp_data_analyzer_main-0.2.0.dist-info/METADATA
mcp_data_analyzer_main-0.2.0.dist-info/WHEEL
mcp_data_analyzer_main-0.2.0.dist-info/entry_points.txt
mcp_data_analyzer_main-0.2.0.dist-info/top_level.txt
mcp_data_analyzer_main-0.2.0.dist-info/RECORD
